kia_hyundai_api/__init__.py
kia_hyundai_api/const.py
kia_hyundai_api/errors.py
kia_hyundai_api/stub.py
kia_hyundai_api/us_kia.py
kia_hyundai_api/util.py
kia_hyundai_api/util_http.py
kia_hyundai_api-1.6.4.dist-info/licenses/LICENSE
kia_hyundai_api-1.6.4.dist-info/METADATA
kia_hyundai_api-1.6.4.dist-info/WHEEL
kia_hyundai_api-1.6.4.dist-info/top_level.txt
kia_hyundai_api-1.6.4.dist-info/RECORD
