Metadata-Version: 2.4
Name: kia_hyundai_api
Version: 1.6.4
Summary: Kia Uvo Api Wrapper
Author-email: Brendan Dahl <dahl.brendan@gmail.com>
Project-URL: Homepage, https://github.com/dahlb/kia_hyundai_api
Project-URL: Bug Tracker, https://github.com/dahlb/kia_hyundai_api/issues
Keywords: Kia,Uvo,rest-mini,api
Classifier: Framework :: AsyncIO
Classifier: Development Status :: 4 - Beta
Classifier: License :: OSI Approved :: MIT License
Classifier: Natural Language :: English
Classifier: Intended Audience :: Developers
Classifier: Programming Language :: Python :: 3.12
Classifier: Operating System :: MacOS :: MacOS X
Requires-Python: <4,>=3.12.0
License-File: LICENSE
Requires-Dist: aiohttp>=3.8.1
Requires-Dist: pytz
Requires-Dist: certifi
Dynamic: license-file
